{
    "cookies": [
        {
            "name": "datr",
            "value": "TNavaTlAN4i5gwpHOpNPF5mi",
            "domain": ".facebook.com",
            "path": "/",
            "expires": 1807691338.467862,
            "httpOnly": true,
            "secure": true,
            "sameSite": "None"
        },
        {
            "name": "fr",
            "value": "02oOcfuxEsW19cgJl..Bpr9ZM..AAA.0.0.Bpr9ZM.AWcFEq7zf4rMYUGAaQC1dWKi3c8",
            "domain": ".facebook.com",
            "path": "/",
            "expires": 1780907338.468285,
            "httpOnly": true,
            "secure": true,
            "sameSite": "None"
        },
        {
            "name": "wd",
            "value": "1280x720",
            "domain": ".facebook.com",
            "path": "/",
            "expires": 1773736181,
            "httpOnly": false,
            "secure": true,
            "sameSite": "Lax"
        },
        {
            "name": "sb",
            "value": "dNavaQUwB4FPddTSJ8yRA7jM",
            "domain": ".facebook.com",
            "path": "/",
            "expires": 1807691379.527206,
            "httpOnly": true,
            "secure": true,
            "sameSite": "None"
        }
    ],
    "origins": [
        {
            "origin": "https://www.facebook.com",
            "localStorage": [
                {
                    "name": "signal_flush_timestamp",
                    "value": "1773131341405"
                },
                {
                    "name": "Session",
                    "value": "kx4tdp:1773131571944"
                },
                {
                    "name": "hb_timestamp",
                    "value": "1773131371417"
                },
                {
                    "name": "banzai:last_storage_flush",
                    "value": "1773131341736.8"
                }
            ]
        },
        {
            "origin": "https://www.google.com",
            "localStorage": [
                {
                    "name": "rc::a",
                    "value": "MWV4cTZtbzFoMXMzOTA="
                }
            ]
        }
    ]
}