{
    "cookies": [
        {
            "name": "datr",
            "value": "EcOvaY5tCJ8Ssu-8Ib2bt0PH",
            "domain": ".facebook.com",
            "path": "/",
            "expires": 1807686415.930018,
            "httpOnly": true,
            "secure": true,
            "sameSite": "None"
        },
        {
            "name": "fr",
            "value": "0L0z1LST418nPutZF..Bpr8MR..AAA.0.0.Bpr8MR.AWfdAV48ANuDjbbIRYKJSqOXjRc",
            "domain": ".facebook.com",
            "path": "/",
            "expires": 1780902415.930408,
            "httpOnly": true,
            "secure": true,
            "sameSite": "None"
        },
        {
            "name": "wd",
            "value": "1280x720",
            "domain": ".facebook.com",
            "path": "/",
            "expires": 1773731351,
            "httpOnly": false,
            "secure": true,
            "sameSite": "Lax"
        },
        {
            "name": "sb",
            "value": "PsOvaQroJKr-docHRhQaRw8D",
            "domain": ".facebook.com",
            "path": "/",
            "expires": 1807686463.330059,
            "httpOnly": true,
            "secure": true,
            "sameSite": "None"
        },
        {
            "name": "ps_l",
            "value": "1",
            "domain": ".facebook.com",
            "path": "/",
            "expires": 1807686551.13673,
            "httpOnly": true,
            "secure": true,
            "sameSite": "Lax"
        },
        {
            "name": "ps_n",
            "value": "1",
            "domain": ".facebook.com",
            "path": "/",
            "expires": 1807686551.136904,
            "httpOnly": true,
            "secure": true,
            "sameSite": "None"
        }
    ],
    "origins": [
        {
            "origin": "https://www.facebook.com",
            "localStorage": [
                {
                    "name": "signal_flush_timestamp",
                    "value": "1773126427873"
                },
                {
                    "name": "Session",
                    "value": "pg5vzk:1773126617119"
                },
                {
                    "name": "hb_timestamp",
                    "value": "1773126457879"
                },
                {
                    "name": "banzai:last_storage_flush",
                    "value": "1773126424109.7002"
                }
            ]
        }
    ]
}