{
    "cookies": [
        {
            "name": "dbln",
            "value": "%7B%22100007670940489%22%3A%227lSsgvbG%22%7D",
            "domain": ".facebook.com",
            "path": "/login/device-based/",
            "expires": -1,
            "httpOnly": true,
            "secure": true,
            "sameSite": "Lax"
        },
        {
            "name": "datr",
            "value": "4ZCgaaFgyUM_y5bcIh0CZu78",
            "domain": ".facebook.com",
            "path": "/",
            "expires": -1,
            "httpOnly": true,
            "secure": true,
            "sameSite": "Lax"
        },
        {
            "name": "sb",
            "value": "lZGgaRojEjowY0FuiEOiiv2o",
            "domain": ".facebook.com",
            "path": "/",
            "expires": -1,
            "httpOnly": true,
            "secure": true,
            "sameSite": "Lax"
        },
        {
            "name": "ps_l",
            "value": "1",
            "domain": ".facebook.com",
            "path": "/",
            "expires": -1,
            "httpOnly": true,
            "secure": true,
            "sameSite": "Lax"
        },
        {
            "name": "ps_n",
            "value": "1",
            "domain": ".facebook.com",
            "path": "/",
            "expires": -1,
            "httpOnly": true,
            "secure": true,
            "sameSite": "Lax"
        },
        {
            "name": "wd",
            "value": "1280x720",
            "domain": ".facebook.com",
            "path": "/",
            "expires": -1,
            "httpOnly": false,
            "secure": true,
            "sameSite": "Lax"
        },
        {
            "name": "c_user",
            "value": "100007670940489",
            "domain": ".facebook.com",
            "path": "/",
            "expires": -1,
            "httpOnly": false,
            "secure": true,
            "sameSite": "Lax"
        },
        {
            "name": "alsfid",
            "value": "{\"id\":\"f4bcfd3c6\",\"timestamp\":1778455017167.8}",
            "domain": ".facebook.com",
            "path": "/",
            "expires": -1,
            "httpOnly": false,
            "secure": false,
            "sameSite": "Lax"
        },
        {
            "name": "ps_l",
            "value": "1",
            "domain": ".fb.com",
            "path": "/",
            "expires": -1,
            "httpOnly": true,
            "secure": true,
            "sameSite": "Lax"
        },
        {
            "name": "ps_n",
            "value": "1",
            "domain": ".fb.com",
            "path": "/",
            "expires": -1,
            "httpOnly": true,
            "secure": true,
            "sameSite": "Lax"
        },
        {
            "name": "presence",
            "value": "C%7B%22t3%22%3A%5B%5D%2C%22utc3%22%3A1784482047369%2C%22v%22%3A1%7D",
            "domain": ".facebook.com",
            "path": "/",
            "expires": -1,
            "httpOnly": false,
            "secure": true,
            "sameSite": "Lax"
        },
        {
            "name": "xs",
            "value": "27%3AJOnTDNfwF22UIg%3A2%3A1778450647%3A-1%3A-1%3A%3AAcwonbaFBqpzLmDaJmQS6F54VJGpuypQm-ZZr0y61vg",
            "domain": ".facebook.com",
            "path": "/",
            "expires": -1,
            "httpOnly": true,
            "secure": true,
            "sameSite": "Lax"
        },
        {
            "name": "fr",
            "value": "1U0PgL4Gosds5Y3Nz.AWftRLeC7X7s5uSdwGXI_5uYFpagj2Iir8GprsNS2S0HH14Y1nk.BqXgon..AAA.0.0.BqXha-.AWfMQbkocrXTJmwBsIwjtP_13Ic",
            "domain": ".facebook.com",
            "path": "/",
            "expires": 1792327102.452863,
            "httpOnly": true,
            "secure": true,
            "sameSite": "None"
        }
    ],
    "origins": [
        {
            "origin": "https://www.facebook.com",
            "localStorage": [
                {
                    "name": "Session",
                    "value": "zvsh70:1784551141425"
                },
                {
                    "name": "mutex_screen_time_period_logging_mutex_100007670940489_facebook",
                    "value": "cxfth6:1784551121933"
                },
                {
                    "name": "mutex_banzai",
                    "value": "cxfth6:1784551107975"
                },
                {
                    "name": "mw_encrypted_backups_restore_upsell_first_impression_time_key",
                    "value": "1784551107245"
                }
            ]
        }
    ]
}