{
    "cookies": [
        {
            "name": "dbln",
            "value": "%7B%22100007670940489%22%3A%227lSsgvbG%22%7D",
            "domain": ".facebook.com",
            "path": "/login/device-based/",
            "expires": -1,
            "httpOnly": true,
            "secure": true,
            "sameSite": "Lax"
        },
        {
            "name": "datr",
            "value": "4ZCgaaFgyUM_y5bcIh0CZu78",
            "domain": ".facebook.com",
            "path": "/",
            "expires": -1,
            "httpOnly": true,
            "secure": true,
            "sameSite": "Lax"
        },
        {
            "name": "sb",
            "value": "lZGgaRojEjowY0FuiEOiiv2o",
            "domain": ".facebook.com",
            "path": "/",
            "expires": -1,
            "httpOnly": true,
            "secure": true,
            "sameSite": "Lax"
        },
        {
            "name": "ps_l",
            "value": "1",
            "domain": ".facebook.com",
            "path": "/",
            "expires": -1,
            "httpOnly": true,
            "secure": true,
            "sameSite": "Lax"
        },
        {
            "name": "ps_n",
            "value": "1",
            "domain": ".facebook.com",
            "path": "/",
            "expires": -1,
            "httpOnly": true,
            "secure": true,
            "sameSite": "Lax"
        },
        {
            "name": "wd",
            "value": "1280x720",
            "domain": ".facebook.com",
            "path": "/",
            "expires": -1,
            "httpOnly": false,
            "secure": true,
            "sameSite": "Lax"
        },
        {
            "name": "c_user",
            "value": "100007670940489",
            "domain": ".facebook.com",
            "path": "/",
            "expires": 1815545835.798109,
            "httpOnly": false,
            "secure": true,
            "sameSite": "None"
        },
        {
            "name": "alsfid",
            "value": "{\"id\":\"f4bcfd3c6\",\"timestamp\":1778455017167.8}",
            "domain": ".facebook.com",
            "path": "/",
            "expires": -1,
            "httpOnly": false,
            "secure": false,
            "sameSite": "Lax"
        },
        {
            "name": "ps_l",
            "value": "1",
            "domain": ".fb.com",
            "path": "/",
            "expires": -1,
            "httpOnly": true,
            "secure": true,
            "sameSite": "Lax"
        },
        {
            "name": "ps_n",
            "value": "1",
            "domain": ".fb.com",
            "path": "/",
            "expires": -1,
            "httpOnly": true,
            "secure": true,
            "sameSite": "Lax"
        },
        {
            "name": "presence",
            "value": "C%7B%22t3%22%3A%5B%5D%2C%22utc3%22%3A1783970184207%2C%22v%22%3A1%7D",
            "domain": ".facebook.com",
            "path": "/",
            "expires": -1,
            "httpOnly": false,
            "secure": true,
            "sameSite": "Lax"
        },
        {
            "name": "fr",
            "value": "1TFgR5djAUZ0Ei1Ew.AWeoBW8ISxlqP-Qn-ucTqzLAMfoH2mMUdt2xXuaqq8mr0iGSpd4.BqVdRs..AAA.0.0.BqVdRs.AWfGbW2-FNzFBkEqXf0pYC4MGjY",
            "domain": ".facebook.com",
            "path": "/",
            "expires": 1791785835.7985,
            "httpOnly": true,
            "secure": true,
            "sameSite": "None"
        },
        {
            "name": "xs",
            "value": "27%3AJOnTDNfwF22UIg%3A2%3A1778450647%3A-1%3A-1%3A%3AAcwbpZ_x4faUIm5-zKHIFmVBIP_vVK9IojC2lUHuJhM",
            "domain": ".facebook.com",
            "path": "/",
            "expires": 1815545835.798622,
            "httpOnly": true,
            "secure": true,
            "sameSite": "None"
        }
    ],
    "origins": [
        {
            "origin": "https://www.facebook.com",
            "localStorage": [
                {
                    "name": "screen_time_period_logging_facebook",
                    "value": "{\"actorId\":\"100007670940489\",\"currentIntervalLastTick\":1784009839,\"currentIntervalStart\":1784009834,\"initRemoteAgg\":{\"timestamp\":1783971699,\"today_s\":0},\"intervals\":[],\"lastCallbackAttempt\":1784009834,\"localStorageId\":\"27262904\",\"syncedL24HS\":null,\"syncedTodayS\":null}"
                },
                {
                    "name": "last_headload_time",
                    "value": "1784009837205"
                },
                {
                    "name": "Session",
                    "value": "u87c4e:1784009865066"
                },
                {
                    "name": "banzai:last_storage_flush",
                    "value": "1784009838245.3"
                },
                {
                    "name": "mw_encrypted_backups_restore_upsell_first_impression_time_key",
                    "value": "1784009834352"
                }
            ]
        }
    ]
}