{
    "cookies": [
        {
            "name": "dbln",
            "value": "%7B%22100055655350537%22%3A%22pp0iNZHO%22%7D",
            "domain": ".facebook.com",
            "path": "/login/device-based/",
            "expires": 1779696954.932738,
            "httpOnly": true,
            "secure": true,
            "sameSite": "None"
        },
        {
            "name": "datr",
            "value": "5F2daS5Ram4N_5uCTe8aDm7F",
            "domain": ".facebook.com",
            "path": "/",
            "expires": 1806480866.171393,
            "httpOnly": true,
            "secure": true,
            "sameSite": "None"
        },
        {
            "name": "wd",
            "value": "1280x720",
            "domain": ".facebook.com",
            "path": "/",
            "expires": 1772525745,
            "httpOnly": false,
            "secure": true,
            "sameSite": "Lax"
        },
        {
            "name": "c_user",
            "value": "100055655350537",
            "domain": ".facebook.com",
            "path": "/",
            "expires": 1803456934.655446,
            "httpOnly": false,
            "secure": true,
            "sameSite": "None"
        },
        {
            "name": "sb",
            "value": "GF6daaCrg7SXgvb0mk2doAHv",
            "domain": ".facebook.com",
            "path": "/",
            "expires": 1806480922.249515,
            "httpOnly": true,
            "secure": true,
            "sameSite": "None"
        },
        {
            "name": "fr",
            "value": "2l9GE11nBry3BOxnk.AWc2MTsiWQZ2_ZIN_3AgvSTyMyJUW7TvNnX6WwxQiz5eczhQaxA.BpnV4o..AAA.0.0.BpnV4o.AWe8JZtI8KYIOe1eP0ekevQOqzk",
            "domain": ".facebook.com",
            "path": "/",
            "expires": 1779696934.655665,
            "httpOnly": true,
            "secure": true,
            "sameSite": "None"
        },
        {
            "name": "xs",
            "value": "45%3AFGfe4YKUDCnfcg%3A2%3A1771920921%3A-1%3A-1%3A%3AAcxPZ1nooB56RtUGFWOc3qaLIQI4ANjOf2iKZLeP5A",
            "domain": ".facebook.com",
            "path": "/",
            "expires": 1803456934.656012,
            "httpOnly": true,
            "secure": true,
            "sameSite": "None"
        },
        {
            "name": "presence",
            "value": "C%7B%22t3%22%3A%5B%5D%2C%22utc3%22%3A1771920949756%2C%22v%22%3A1%7D",
            "domain": ".facebook.com",
            "path": "/",
            "expires": -1,
            "httpOnly": false,
            "secure": true,
            "sameSite": "Lax"
        }
    ],
    "origins": [
        {
            "origin": "https://www.facebook.com",
            "localStorage": [
                {
                    "name": "mw_encrypted_backups_restore_upsell_first_impression_time_key",
                    "value": "1771920942533"
                },
                {
                    "name": "Session",
                    "value": "0ym9tr:1771921080125"
                },
                {
                    "name": "banzai:last_storage_flush",
                    "value": "1771920870379.6"
                },
                {
                    "name": "screen_time_period_logging_facebook",
                    "value": "{\"actorId\":\"100055655350537\",\"currentIntervalLastTick\":1771921070,\"currentIntervalStart\":1771920934,\"initRemoteAgg\":{\"timestamp\":-1,\"today_s\":0},\"intervals\":[],\"lastCallbackAttempt\":1771920934,\"localStorageId\":\"13501932\",\"syncedL24HS\":null,\"syncedTodayS\":null}"
                },
                {
                    "name": "last_headload_time",
                    "value": "1771920934730"
                },
                {
                    "name": "RSTData",
                    "value": "{}"
                },
                {
                    "name": "hb_timestamp",
                    "value": "1771920900202"
                },
                {
                    "name": "bdz_playback_state",
                    "value": "{\"session_key\":\"mlm1kslp\",\"buffer_length\":60}"
                },
                {
                    "name": "ares_last_signal_flush",
                    "value": "1771056944845"
                },
                {
                    "name": "signal_flush_timestamp",
                    "value": "1771920870229"
                },
                {
                    "name": "topicsLastReportingTime",
                    "value": "1771920950019"
                }
            ]
        }
    ]
}