{
    "cookies": [
        {
            "name": "dbln",
            "value": "%7B%22100055655350537%22%3A%22pp0iNZHO%22%7D",
            "domain": ".facebook.com",
            "path": "/login/device-based/",
            "expires": 1779696954.932738,
            "httpOnly": true,
            "secure": true,
            "sameSite": "None"
        },
        {
            "name": "datr",
            "value": "5F2daS5Ram4N_5uCTe8aDm7F",
            "domain": ".facebook.com",
            "path": "/",
            "expires": 1806480866.171393,
            "httpOnly": true,
            "secure": true,
            "sameSite": "None"
        },
        {
            "name": "c_user",
            "value": "100055655350537",
            "domain": ".facebook.com",
            "path": "/",
            "expires": 1808292534.584396,
            "httpOnly": false,
            "secure": true,
            "sameSite": "None"
        },
        {
            "name": "sb",
            "value": "GF6daaCrg7SXgvb0mk2doAHv",
            "domain": ".facebook.com",
            "path": "/",
            "expires": 1806480922.249515,
            "httpOnly": true,
            "secure": true,
            "sameSite": "None"
        },
        {
            "name": "wd",
            "value": "1280x720",
            "domain": ".facebook.com",
            "path": "/",
            "expires": 1777361337,
            "httpOnly": false,
            "secure": true,
            "sameSite": "Lax"
        },
        {
            "name": "i_user",
            "value": "61573227222459",
            "domain": ".facebook.com",
            "path": "/",
            "expires": 1807955348.64783,
            "httpOnly": false,
            "secure": true,
            "sameSite": "None"
        },
        {
            "name": "fr",
            "value": "1NmVhw7neOIWc7bTO.AWc89D6JEl2yNCxM0NXdtYN7q1IKQLtnwyOC6a2Mm9aIBYesS38.Bp5yc1..AAA.0.0.Bp5yc1.AWcSFhdktcBOUOQS5cPYNN_NnZ0",
            "domain": ".facebook.com",
            "path": "/",
            "expires": 1784532534.584592,
            "httpOnly": true,
            "secure": true,
            "sameSite": "None"
        },
        {
            "name": "xs",
            "value": "45%3AFGfe4YKUDCnfcg%3A2%3A1771920921%3A-1%3A-1%3A%3AAcw4GBR_StMEMuFpyk5fP79hHnJa6COfl11SRm8oYT4",
            "domain": ".facebook.com",
            "path": "/",
            "expires": 1808292534.584733,
            "httpOnly": true,
            "secure": true,
            "sameSite": "None"
        }
    ],
    "origins": [
        {
            "origin": "https://www.facebook.com",
            "localStorage": [
                {
                    "name": "armadillo_msgr_data_loss_stats",
                    "value": "{}"
                },
                {
                    "name": "ps:61573227222459:d7efc90a-165e-43f2-b498-74b8d9f2103b",
                    "value": "588681b6-5684-4375-98b8-7b490ac2ba75:1776756612560"
                },
                {
                    "name": "CacheStorageVersion",
                    "value": "3b"
                },
                {
                    "name": "Session",
                    "value": "ok4bpx:1776756649196"
                },
                {
                    "name": "_oz_bandwidthEstimate",
                    "value": "6650000"
                },
                {
                    "name": "banzai:last_storage_flush",
                    "value": "1776756538537.7002"
                },
                {
                    "name": "screen_time_period_logging_facebook",
                    "value": "{\"actorId\":\"61573227222459\",\"currentIntervalLastTick\":1776756683,\"currentIntervalStart\":1776756533,\"initRemoteAgg\":{\"timestamp\":-1,\"today_s\":0},\"intervals\":[{\"end\":1776419390,\"start\":1776419355}],\"lastCallbackAttempt\":1776756533,\"localStorageId\":\"86352433\",\"syncedL24HS\":null,\"syncedTodayS\":null}"
                },
                {
                    "name": "last_headload_time",
                    "value": "1776756533600"
                },
                {
                    "name": "RSTData",
                    "value": "{}"
                },
                {
                    "name": "bdz_playback_state",
                    "value": "{\"session_key\":\"mnoftcrp\",\"buffer_length\":60}"
                },
                {
                    "name": "hb_timestamp",
                    "value": "1776756568473"
                },
                {
                    "name": "_oz_bandwidthAndTTFBSamples",
                    "value": "{\"b\":[],\"t\":[]}"
                },
                {
                    "name": "ares_last_signal_flush",
                    "value": "1775555355877"
                },
                {
                    "name": "signal_flush_timestamp",
                    "value": "1776756538473"
                }
            ]
        },
        {
            "origin": "https://business.facebook.com",
            "localStorage": [
                {
                    "name": "signal_flush_timestamp",
                    "value": "1776751005204"
                },
                {
                    "name": "RSTData",
                    "value": "{}"
                },
                {
                    "name": "Session",
                    "value": "y1ivca:1776751047250"
                },
                {
                    "name": "hb_timestamp",
                    "value": "1776751005102"
                },
                {
                    "name": "mutex_banzai",
                    "value": "rkix67:1776750997332"
                },
                {
                    "name": "banzai:last_storage_flush",
                    "value": "1776725774038"
                }
            ]
        }
    ]
}