{
    "cookies": [
        {
            "name": "dbln",
            "value": "%7B%22100029155272922%22%3A%22wSFSZ6RJ%22%7D",
            "domain": ".facebook.com",
            "path": "/login/device-based/",
            "expires": 1785751697.487236,
            "httpOnly": true,
            "secure": true,
            "sameSite": "None"
        },
        {
            "name": "datr",
            "value": "yJKgaVg8hCSBzGSyPZvgBNn-",
            "domain": ".facebook.com",
            "path": "/",
            "expires": 1806691014.344674,
            "httpOnly": true,
            "secure": true,
            "sameSite": "None"
        },
        {
            "name": "sb",
            "value": "-ZKgaSVP8ESzqsGz1wMz0OSt",
            "domain": ".facebook.com",
            "path": "/",
            "expires": 1812535697.48804,
            "httpOnly": true,
            "secure": true,
            "sameSite": "None"
        },
        {
            "name": "wd",
            "value": "1280x720",
            "domain": ".facebook.com",
            "path": "/",
            "expires": 1778580507,
            "httpOnly": false,
            "secure": true,
            "sameSite": "Lax"
        },
        {
            "name": "ps_l",
            "value": "1",
            "domain": ".facebook.com",
            "path": "/",
            "expires": 1811355059.831818,
            "httpOnly": true,
            "secure": true,
            "sameSite": "Lax"
        },
        {
            "name": "ps_n",
            "value": "1",
            "domain": ".facebook.com",
            "path": "/",
            "expires": 1811355059.832022,
            "httpOnly": true,
            "secure": true,
            "sameSite": "None"
        },
        {
            "name": "c_user",
            "value": "100029155272922",
            "domain": ".facebook.com",
            "path": "/",
            "expires": 1809511701.070642,
            "httpOnly": false,
            "secure": true,
            "sameSite": "None"
        },
        {
            "name": "xs",
            "value": "48%3A2Ivpnf2pn6sMJQ%3A2%3A1777975696%3A-1%3A-1%3A%3AAczqYDG7sPx0-_cXUQ0-TCBgQonRYtO9ur1FBi0cyg",
            "domain": ".facebook.com",
            "path": "/",
            "expires": 1809511701.070987,
            "httpOnly": true,
            "secure": true,
            "sameSite": "None"
        },
        {
            "name": "fr",
            "value": "1pc4MwuPgvJcvn6r8.AWdprxbTW3gMceH0Rgi7sZSs6I7XmRxzcA3Zysa6vNm_4JRIiTk.Bp-cGW..AAA.0.0.Bp-cGZ.AWcW7gj2uCPk_c8SJST_r6SrPVs",
            "domain": ".facebook.com",
            "path": "/",
            "expires": 1785751703.891123,
            "httpOnly": true,
            "secure": true,
            "sameSite": "None"
        },
        {
            "name": "presence",
            "value": "C%7B%22t3%22%3A%5B%5D%2C%22utc3%22%3A1777975713358%2C%22v%22%3A1%7D",
            "domain": ".facebook.com",
            "path": "/",
            "expires": -1,
            "httpOnly": false,
            "secure": true,
            "sameSite": "Lax"
        }
    ],
    "origins": [
        {
            "origin": "https://www.facebook.com",
            "localStorage": [
                {
                    "name": "armadillo_msgr_data_loss_stats",
                    "value": "{}"
                },
                {
                    "name": "CacheStorageVersion",
                    "value": "3b"
                },
                {
                    "name": "mw_encrypted_backups_restore_upsell_first_impression_time_key",
                    "value": "1777975708023"
                },
                {
                    "name": "Session",
                    "value": "y5t4w7:1777975752567"
                },
                {
                    "name": "_oz_bandwidthEstimate",
                    "value": "10000000"
                },
                {
                    "name": "banzai:last_storage_flush",
                    "value": "1777975399771.2002"
                },
                {
                    "name": "screen_time_period_logging_facebook",
                    "value": "{\"actorId\":\"100029155272922\",\"currentIntervalLastTick\":1777975718,\"currentIntervalStart\":1777975706,\"initRemoteAgg\":{\"timestamp\":1777935833,\"today_s\":231},\"intervals\":[],\"lastCallbackAttempt\":1777975706,\"localStorageId\":\"17505911\",\"syncedL24HS\":null,\"syncedTodayS\":null}"
                },
                {
                    "name": "last_headload_time",
                    "value": "1777975706490"
                },
                {
                    "name": "RSTData",
                    "value": "{}"
                },
                {
                    "name": "bdz_playback_state",
                    "value": "{\"session_key\":\"mnvb33sr\",\"buffer_length\":60}"
                },
                {
                    "name": "hb_timestamp",
                    "value": "1777975399199"
                },
                {
                    "name": "_oz_bandwidthAndTTFBSamples",
                    "value": "{\"b\":[],\"t\":[]}"
                },
                {
                    "name": "ps:100083164069089:bff1322f-a548-476d-a37a-a88af2a0c3b2",
                    "value": "e9ea4e2b-1820-4d59-b981-aa90384aabf0:1776834817574"
                },
                {
                    "name": "ares_last_signal_flush",
                    "value": "1775970675963"
                },
                {
                    "name": "signal_flush_timestamp",
                    "value": "1777975399264"
                }
            ]
        },
        {
            "origin": "https://business.facebook.com",
            "localStorage": [
                {
                    "name": "signal_flush_timestamp",
                    "value": "1777790058296"
                },
                {
                    "name": "RSTData",
                    "value": "{}"
                },
                {
                    "name": "Session",
                    "value": "npyif2:1777790097654"
                },
                {
                    "name": "hb_timestamp",
                    "value": "1777790058235"
                },
                {
                    "name": "banzai:last_storage_flush",
                    "value": "1777790056116.9"
                }
            ]
        }
    ]
}